setup.py
cocaine/pipeline/__init__.py
cocaine_pipeline_cli.egg-info/PKG-INFO
cocaine_pipeline_cli.egg-info/SOURCES.txt
cocaine_pipeline_cli.egg-info/dependency_links.txt
cocaine_pipeline_cli.egg-info/entry_points.txt
cocaine_pipeline_cli.egg-info/namespace_packages.txt
cocaine_pipeline_cli.egg-info/not-zip-safe
cocaine_pipeline_cli.egg-info/requires.txt
cocaine_pipeline_cli.egg-info/top_level.txt