Metadata-Version: 1.1
Name: cocaine-pipeline-cli
Version: 0.11.6.4
Summary: Cocaine Tools for Cocaine Application Cloud.
Home-page: UNKNOWN
Author: Anton Tyurin
Author-email: noxiouz@yandex.ru
License: LGPLv3+
Platform: Linux
Platform: BSD
Platform: MacOS
Classifier: Development Status :: 5 - Production/Stable
